tasklogger/__init__.py
tasklogger/api.py
tasklogger/logger.py
tasklogger/version.py
tasklogger-1.2.0.dist-info/LICENSE
tasklogger-1.2.0.dist-info/METADATA
tasklogger-1.2.0.dist-info/WHEEL
tasklogger-1.2.0.dist-info/top_level.txt
tasklogger-1.2.0.dist-info/RECORD
