Metadata-Version: 2.1
Name: tasklogger
Version: 1.2.0
Summary: tasklogger
Home-page: https://github.com/scottgigante/tasklogger
Download-URL: https://github.com/scottgigante/tasklogger/archive/v1.2.0.tar.gz
Author: Scott Gigante, Yale University
Author-email: scott.gigante@yale.edu
License: GNU General Public License Version 2
Keywords: big-data,tool-development,programming
Classifier: Development Status :: 5 - Production/Stable
Classifier: Environment :: Console
Classifier: Framework :: Jupyter
Classifier: Intended Audience :: Developers
Classifier: Intended Audience :: Science/Research
Classifier: Natural Language :: English
Classifier: Operating System :: MacOS :: MacOS X
Classifier: Operating System :: Microsoft :: Windows
Classifier: Operating System :: POSIX :: Linux
Classifier: Programming Language :: Python :: 2
Classifier: Programming Language :: Python :: 2.7
Classifier: Programming Language :: Python :: 3
Classifier: Programming Language :: Python :: 3.5
Classifier: Programming Language :: Python :: 3.6
Classifier: Topic :: Scientific/Engineering :: Mathematics
Requires-Python: >=3.6
License-File: LICENSE
Requires-Dist: Deprecated
Provides-Extra: test
Requires-Dist: nose2 ; extra == 'test'
Requires-Dist: numpy ; extra == 'test'
Requires-Dist: coverage ; extra == 'test'
Requires-Dist: coveralls ; extra == 'test'
